MANIFEST.in
__info__.py
setup.py
./appomatic_admin.egg-info/SOURCES.txt
./appomatic_admin.egg-info/dependency_links.txt
./appomatic_admin.egg-info/requires.txt
./appomatic_admin.egg-info/top_level.txt
appomatic_admin/__app__.py
appomatic_admin/__init__.py
appomatic_admin/__urls__.py
appomatic_admin.egg-info/PKG-INFO
appomatic_admin.egg-info/SOURCES.txt
appomatic_admin.egg-info/dependency_links.txt
appomatic_admin.egg-info/requires.txt
appomatic_admin.egg-info/top_level.txt