Metadata-Version: 1.0
Name: appomatic-admin
Version: 0.0.31
Summary: Enables the django site admin
Home-page: http://github.com/redhog/appomatic
Author: RedHog (Egil Moeller)
Author-email: egil.moller@freecode.no
License: GPL
Keywords: appomatic admin
Platform: UNKNOWN
